{
	"credit": "Made with Blockbench",
	"texture_size": [8, 8],
	"textures": {
		"0": "nukacraft:items/tier1magazine",
		"particle": "nukacraft:items/tier1magazine"
	},
	"elements": [
		{
			"from": [7.2, 6.2, 6.9],
			"to": [8.8, 8.4, 8.9],
			"faces": {
				"north": {"uv": [0, 6, 3.25, 10.5], "texture": "#0"},
				"east": {"uv": [0, 0, 4, 4.5], "texture": "#0"},
				"south": {"uv": [4, 6, 7.25, 10.5], "texture": "#0"},
				"west": {"uv": [4, 0, 8, 4.5], "texture": "#0"},
				"up": {"uv": [11.25, 4, 8, 0], "texture": "#0"},
				"down": {"uv": [11.25, 4, 8, 8], "texture": "#0"}
			}
		},
		{
			"from": [7.18, 8.326, 6.9],
			"to": [8.78, 8.326, 8.9],
			"rotation": {"angle": 22.5, "axis": "z", "origin": [7, 8.4, 7.9]},
			"faces": {
				"north": {"uv": [0, 0, 3.25, 0], "texture": "#0"},
				"east": {"uv": [0, 0, 4, 0], "texture": "#0"},
				"south": {"uv": [0, 0, 3.25, 0], "texture": "#0"},
				"west": {"uv": [0, 0, 4, 0], "texture": "#0"},
				"up": {"uv": [11.25, 12, 8, 8], "texture": "#0"},
				"down": {"uv": [3.25, 12, 0, 16], "texture": "#0"}
			}
		},
		{
			"from": [8.78, 8.13, 6.9],
			"to": [8.78, 8.33, 8.9],
			"rotation": {"angle": 22.5, "axis": "z", "origin": [7, 8.4, 7.9]},
			"faces": {
				"north": {"uv": [0, 0, 0, 0.5], "texture": "#0"},
				"east": {"uv": [12, 0, 16, 0.5], "texture": "#0"},
				"south": {"uv": [0, 0, 0, 0.5], "texture": "#0"},
				"west": {"uv": [12, 2, 16, 2.5], "texture": "#0"},
				"up": {"uv": [0, 4, 0, 0], "texture": "#0"},
				"down": {"uv": [0, 0, 0, 4], "texture": "#0"}
			}
		}
	],
	"display": {
		"thirdperson_righthand": {
			"rotation": [90, 90, -36],
			"translation": [0, 1.25, 1.75],
			"scale": [1.2, 1.2, 1.2]
		},
		"thirdperson_lefthand": {
			"rotation": [39, -91, 0],
			"translation": [0, 0.75, 1.25]
		},
		"firstperson_righthand": {
			"rotation": [0, -163, -11],
			"translation": [-3.75, 5.25, 5.5]
		},
		"firstperson_lefthand": {
			"rotation": [0, 15, 0],
			"translation": [-3.25, 5, 5.75]
		},
		"ground": {
			"translation": [0, -0.25, 0],
			"scale": [1.5, 1.5, 1.5]
		},
		"gui": {
			"rotation": [30, 225, 0],
			"translation": [-0.25, 2.25, 0],
			"scale": [4, 4, 4]
		},
		"fixed": {
			"rotation": [0, 90, -17],
			"translation": [-0.25, 1.25, -1],
			"scale": [3.48, 3.48, 3.48]
		}
	},
	"groups": [
		{
			"name": "magazinet1",
			"origin": [8, 8, 8],
			"color": 0,
			"children": [0, 1, 2]
		}
	]
}