{
	"format_version": "1.12.0",
	"minecraft:geometry": [
		{
			"description": {
				"identifier": "geometry.unknown",
				"texture_width": 64,
				"texture_height": 64,
				"visible_bounds_width": 3,
				"visible_bounds_height": 3.5,
				"visible_bounds_offset": [0, 1.25, 0]
			},
			"bones": [
				{
					"name": "bipedHead",
					"pivot": [0, 24, 0]
				},
				{
					"name": "armorHead",
					"parent": "bipedHead",
					"pivot": [0, 23.1, 0],
					"cubes": [
						{
							"origin": [-4.77603, 29.46804, -4.77603],
							"size": [9.66577, 3.7526, 9.55206],
							"pivot": [0.05686, 31.28748, -0.05686],
							"rotation": [-5, 0, 0],
							"uv": {
								"north": {"uv": [50, 4], "uv_size": [8, 3]},
								"east": {"uv": [40, 0], "uv_size": [9, 3]},
								"south": {"uv": [50, 0], "uv_size": [8, 3]},
								"west": {"uv": [40, 4], "uv_size": [9, 3]},
								"up": {"uv": [58, 16], "uv_size": [-8, -8]},
								"down": {"uv": [47, 22], "uv_size": [-8, -8]}
							}
						},
						{
							"origin": [-2.50173, 29.46804, -8.19885],
							"size": [5.23089, 1.02344, 3.52517],
							"pivot": [0.17057, 31.28748, -0.05686],
							"rotation": [-5, 0, 0],
							"uv": {
								"north": {"uv": [40, 11], "uv_size": [5, 1]},
								"east": {"uv": [40, 11], "uv_size": [3, 1]},
								"south": {"uv": [40, 11], "uv_size": [5, 1]},
								"west": {"uv": [40, 11], "uv_size": [3, 1]},
								"up": {"uv": [45, 14], "uv_size": [-5, -3]},
								"down": {"uv": [45, 11], "uv_size": [-5, 3]}
							}
						},
						{
							"origin": [-4.51449, 30.45736, -8.27701],
							"size": [2.16058, 1.02344, 3.41145],
							"pivot": [0.05686, 30.5447, -6.57128],
							"rotation": [-5, 0, -10],
							"uv": {
								"north": {"uv": [51, 19], "uv_size": [2, 1]},
								"east": {"uv": [51, 17], "uv_size": [3, 1]},
								"south": {"uv": [49, 17], "uv_size": [2, 1]},
								"west": {"uv": [51, 18], "uv_size": [3, 1]},
								"up": {"uv": [53, 23], "uv_size": [-2, -3]},
								"down": {"uv": [51, 21], "uv_size": [-2, -3]}
							}
						},
						{
							"origin": [2.3539, 30.45736, -8.27701],
							"size": [2.16058, 1.02344, 3.41145],
							"pivot": [-0.05686, 30.5447, -6.57128],
							"rotation": [-5, 0, 10],
							"uv": {
								"north": {"uv": [53, 19], "uv_size": [-2, 1]},
								"east": {"uv": [54, 18], "uv_size": [-3, 1]},
								"south": {"uv": [51, 17], "uv_size": [-2, 1]},
								"west": {"uv": [54, 17], "uv_size": [-3, 1]},
								"up": {"uv": [51, 23], "uv_size": [2, -3]},
								"down": {"uv": [49, 21], "uv_size": [2, -3]}
							}
						},
						{
							"origin": [-4.88974, 30.37776, -4.88975],
							"size": [9.8932, 1.13715, 10.23435],
							"pivot": [0.05686, 32.1972, 0.22743],
							"rotation": [-10, 0, 0],
							"uv": {
								"north": {"uv": [38, 35], "uv_size": [8.7, 1]},
								"east": {"uv": [38, 35], "uv_size": [9, 1]},
								"south": {"uv": [38.1, 35], "uv_size": [8.7, 1]},
								"west": {"uv": [38, 35], "uv_size": [9, 1]},
								"up": {"uv": [2.7, 9], "uv_size": [-1.7, -3]},
								"down": {"uv": [3.7, 5], "uv_size": [-2.7, -3]}
							}
						},
						{
							"origin": [-4.09374, 30.94633, -5.45832],
							"size": [3.07031, 2.2743, 0.79601],
							"pivot": [-1.99001, 32.08348, -5.06032],
							"rotation": [-12.5, 7.5, 0],
							"uv": {
								"north": {"uv": [4, 39], "uv_size": [3, 2]},
								"east": {"uv": [7, 40], "uv_size": [1, 2]},
								"south": {"uv": [0, 0], "uv_size": [2.7, 2]},
								"west": {"uv": [7, 40], "uv_size": [1, 2]},
								"up": {"uv": [7, 41.7], "uv_size": [-3, -0.7]},
								"down": {"uv": [7, 42], "uv_size": [-3, -1]}
							}
						},
						{
							"origin": [1.13715, 30.94633, -5.45832],
							"size": [3.07031, 2.2743, 0.79601],
							"pivot": [1.99001, 32.08348, -5.06032],
							"rotation": [-12.5, -7.5, 0],
							"uv": {
								"north": {"uv": [7, 39], "uv_size": [-3, 2]},
								"east": {"uv": [8, 40], "uv_size": [-1, 2]},
								"south": {"uv": [2.7, 0], "uv_size": [-2.7, 2]},
								"west": {"uv": [8, 40], "uv_size": [-1, 2]},
								"up": {"uv": [4, 41.7], "uv_size": [3, -0.7]},
								"down": {"uv": [4, 42], "uv_size": [3, -1]}
							}
						}
					]
				},
				{
					"name": "bipedBody",
					"pivot": [0, 24, 0]
				},
				{
					"name": "armorBody",
					"parent": "bipedBody",
					"pivot": [0, 24, 0],
					"cubes": [
						{
							"origin": [-3.675, 18.12, -2.625],
							"size": [3.99, 4.935, 5.145],
							"pivot": [-2.2575, 21.5325, -2.3625],
							"rotation": [0, 0, -17],
							"uv": {
								"north": {"uv": [10, 19], "uv_size": [4, 5]},
								"east": {"uv": [0, 19], "uv_size": [5, 5]},
								"south": {"uv": [14, 19], "uv_size": [4, 5]},
								"west": {"uv": [5, 19], "uv_size": [5, 5]},
								"up": {"uv": [18, 19], "uv_size": [4, 5]},
								"down": {"uv": [22, 15], "uv_size": [4, -5]}
							}
						},
						{
							"origin": [-4.47394, 13.60514, -2.415],
							"size": [8.925, 2.31, 4.725],
							"uv": {
								"north": {"uv": [23, 5], "uv_size": [8, 2]},
								"east": {"uv": [29, 3], "uv_size": [5, 2]},
								"south": {"uv": [23, 7], "uv_size": [8, 2]},
								"west": {"uv": [2, 31], "uv_size": [5, 2]},
								"up": {"uv": [0, 9], "uv_size": [8, 5]},
								"down": {"uv": [8, 14], "uv_size": [8, -5]}
							}
						},
						{
							"origin": [-1.11394, 11.08514, -2.31],
							"size": [2.625, 2.52, 4.515],
							"uv": {
								"north": {"uv": [26, 13], "uv_size": [2, 2]},
								"east": {"uv": [31, 6], "uv_size": [4, 2]},
								"south": {"uv": [27, 33], "uv_size": [2, 2]},
								"west": {"uv": [7, 31], "uv_size": [4, 2]},
								"up": {"uv": [14, 5], "uv_size": [2, 4]},
								"down": {"uv": [20, 14], "uv_size": [2, -4]}
							}
						},
						{
							"origin": [-4.47394, 12.13514, -2.415],
							"size": [8.925, 1.05, 4.725],
							"pivot": [-0.01144, 12.66014, -0.0525],
							"rotation": [0, 0, 5],
							"uv": {
								"north": {"uv": [30, 12], "uv_size": [8, 1]},
								"east": {"uv": [22, 33], "uv_size": [5, 1]},
								"south": {"uv": [31, 5], "uv_size": [8, 1]},
								"west": {"uv": [32, 33], "uv_size": [5, 1]},
								"up": {"uv": [10, 0], "uv_size": [8, 5]},
								"down": {"uv": [0, 19], "uv_size": [8, -5]}
							}
						},
						{
							"origin": [-3.52894, 19.06514, -2.415],
							"size": [7.455, 1.05, 4.725],
							"pivot": [-0.01144, 12.66014, -0.0525],
							"rotation": [0, 0, 5],
							"uv": {
								"north": {"uv": [31, 8], "uv_size": [7, 1]},
								"east": {"uv": [0, 34], "uv_size": [5, 1]},
								"south": {"uv": [32, 21], "uv_size": [7, 1]},
								"west": {"uv": [34, 3], "uv_size": [5, 1]},
								"up": {"uv": [8, 14], "uv_size": [7, 5]},
								"down": {"uv": [15, 19], "uv_size": [7, -5]}
							}
						},
						{
							"origin": [-2.61075, 20.80546, -2.415],
							"size": [7.455, 1.05, 4.725],
							"pivot": [0.80175, 19.54546, -0.0525],
							"rotation": [0, 0, -10],
							"uv": {
								"north": {"uv": [0, 33], "uv_size": [7, 1]},
								"east": {"uv": [34, 4], "uv_size": [5, 1]},
								"south": {"uv": [33, 0], "uv_size": [7, 1]},
								"west": {"uv": [34, 9], "uv_size": [5, 1]},
								"up": {"uv": [16, 5], "uv_size": [7, 5]},
								"down": {"uv": [18, 5], "uv_size": [7, -5]}
							}
						},
						{
							"origin": [-2.73, 14.55, -2.52],
							"size": [1.89, 9.765, 4.935],
							"pivot": [-2.2575, 21.5325, -2.3625],
							"rotation": [0, 0, -17],
							"uv": {
								"north": {"uv": [22, 15], "uv_size": [2, 9]},
								"east": {"uv": [0, 0], "uv_size": [5, 9]},
								"south": {"uv": [0, 24], "uv_size": [2, 9]},
								"west": {"uv": [5, 0], "uv_size": [5, 9]},
								"up": {"uv": [30, 25], "uv_size": [2, 5]},
								"down": {"uv": [30, 35], "uv_size": [2, -5]}
							}
						}
					]
				},
				{
					"name": "bipedRightArm",
					"pivot": [-4, 22, 0]
				},
				{
					"name": "armorRightArm",
					"parent": "bipedRightArm",
					"pivot": [-3.7, 22, 0],
					"cubes": [
						{
							"origin": [-8.99, 23.495, -2.53],
							"size": [2.3, 1.15, 4.945],
							"pivot": [-7.495, 24.3, 0],
							"rotation": [0, 0, -20],
							"uv": {
								"north": {"uv": [23, 9], "uv_size": [2, 1]},
								"east": {"uv": [25, 4], "uv_size": [4, 1]},
								"south": {"uv": [24, 23], "uv_size": [2, 1]},
								"west": {"uv": [34, 10], "uv_size": [4, 1]},
								"up": {"uv": [11, 31], "uv_size": [2, 4]},
								"down": {"uv": [13, 35], "uv_size": [2, -4]}
							}
						},
						{
							"origin": [-8.875, 22.345, -2.415],
							"size": [4.255, 1.265, 4.738],
							"pivot": [-7.495, 24.3, 0],
							"rotation": [0, 0, -20],
							"uv": {
								"north": {"uv": [34, 22], "uv_size": [4, 1]},
								"east": {"uv": [34, 23], "uv_size": [4, 1]},
								"south": {"uv": [34, 24], "uv_size": [4, 1]},
								"west": {"uv": [32, 34], "uv_size": [4, 1]},
								"up": {"uv": [10, 5], "uv_size": [4, 4]},
								"down": {"uv": [16, 14], "uv_size": [4, -4]}
							}
						},
						{
							"origin": [-9.0245, 20.7695, -2.4725],
							"size": [1.035, 3.335, 4.83],
							"uv": {
								"north": {"uv": [5, 36], "uv_size": [1, 3]},
								"east": {"uv": [2, 28], "uv_size": [4, 3]},
								"south": {"uv": [6, 36], "uv_size": [1, 3]},
								"west": {"uv": [6, 28], "uv_size": [4, 3]},
								"up": {"uv": [10, 33], "uv_size": [1, 4]},
								"down": {"uv": [29, 37], "uv_size": [1, -4]}
							}
						},
						{
							"origin": [-8.7945, 18.0095, -1.8975],
							"size": [1.035, 2.76, 3.795],
							"pivot": [-8.392, 19.3895, 0],
							"rotation": [0, 0, -5],
							"uv": {
								"north": {"uv": [14, 36], "uv_size": [1, 2]},
								"east": {"uv": [27, 31], "uv_size": [3, 2]},
								"south": {"uv": [15, 36], "uv_size": [1, 2]},
								"west": {"uv": [33, 1], "uv_size": [3, 2]},
								"up": {"uv": [13, 36], "uv_size": [1, 3]},
								"down": {"uv": [36, 16], "uv_size": [1, -3]}
							}
						},
						{
							"origin": [-8.4495, 18.4695, -2.3575],
							"size": [4.83, 1.84, 4.715],
							"pivot": [-6.0345, 19.3895, 0],
							"rotation": [0, 0, 5],
							"uv": {
								"north": {"uv": [19, 31], "uv_size": [4, 2]},
								"east": {"uv": [23, 31], "uv_size": [4, 2]},
								"south": {"uv": [32, 13], "uv_size": [4, 2]},
								"west": {"uv": [32, 15], "uv_size": [4, 2]},
								"up": {"uv": [2, 24], "uv_size": [4, 4]},
								"down": {"uv": [6, 28], "uv_size": [4, -4]}
							}
						},
						{
							"origin": [-8.5645, 10.9945, -2.3575],
							"size": [4.945, 3.68, 4.715],
							"uv": {
								"north": {"uv": [10, 28], "uv_size": [4, 3]},
								"east": {"uv": [28, 13], "uv_size": [4, 3]},
								"south": {"uv": [14, 28], "uv_size": [4, 3]},
								"west": {"uv": [28, 16], "uv_size": [4, 3]},
								"up": {"uv": [10, 24], "uv_size": [4, 4]},
								"down": {"uv": [14, 28], "uv_size": [4, -4]}
							}
						},
						{
							"origin": [-8.4495, 14.6745, -1.4375],
							"size": [0.345, 1.38, 2.875],
							"pivot": [-8.392, 15.3645, 0],
							"rotation": [0, 0, 7.5],
							"uv": {
								"north": {"uv": [25, 9], "uv_size": [1, 1]},
								"east": {"uv": [36, 2], "uv_size": [2, 1]},
								"south": {"uv": [26, 34], "uv_size": [1, 1]},
								"west": {"uv": [16, 36], "uv_size": [2, 1]},
								"up": {"uv": [36, 16], "uv_size": [1, 2]},
								"down": {"uv": [18, 38], "uv_size": [1, -2]}
							}
						},
						{
							"origin": [-6.8395, 23.8745, -2.4725],
							"size": [2.53, 1.035, 4.83],
							"uv": {
								"north": {"uv": [28, 22], "uv_size": [2, 1]},
								"east": {"uv": [34, 11], "uv_size": [4, 1]},
								"south": {"uv": [36, 1], "uv_size": [2, 1]},
								"west": {"uv": [22, 34], "uv_size": [4, 1]},
								"up": {"uv": [15, 31], "uv_size": [2, 4]},
								"down": {"uv": [17, 35], "uv_size": [2, -4]}
							}
						}
					]
				},
				{
					"name": "bipedLeftArm",
					"pivot": [4, 22, 0]
				},
				{
					"name": "armorLeftArm",
					"parent": "bipedLeftArm",
					"pivot": [3.7, 22, 0],
					"cubes": [
						{
							"origin": [6.67024, 23.48512, -2.51328],
							"size": [2.2848, 1.1424, 4.91232],
							"pivot": [7.46992, 24.2848, 0],
							"rotation": [0, 0, 20],
							"uv": {
								"north": {"uv": [25, 9], "uv_size": [-2, 1]},
								"east": {"uv": [38, 10], "uv_size": [-4, 1]},
								"south": {"uv": [26, 23], "uv_size": [-2, 1]},
								"west": {"uv": [29, 4], "uv_size": [-4, 1]},
								"up": {"uv": [13, 31], "uv_size": [-2, 4]},
								"down": {"uv": [15, 35], "uv_size": [-2, -4]}
							}
						},
						{
							"origin": [4.61392, 22.34272, -2.39904],
							"size": [4.22688, 1.25664, 4.70669],
							"pivot": [7.46992, 24.2848, 0],
							"rotation": [0, 0, 20],
							"uv": {
								"north": {"uv": [38, 22], "uv_size": [-4, 1]},
								"east": {"uv": [36, 34], "uv_size": [-4, 1]},
								"south": {"uv": [38, 24], "uv_size": [-4, 1]},
								"west": {"uv": [38, 23], "uv_size": [-4, 1]},
								"up": {"uv": [14, 5], "uv_size": [-4, 4]},
								"down": {"uv": [20, 14], "uv_size": [-4, -4]}
							}
						},
						{
							"origin": [7.96115, 20.77763, -2.45616],
							"size": [1.02816, 3.31296, 4.79808],
							"uv": {
								"north": {"uv": [6, 36], "uv_size": [-1, 3]},
								"east": {"uv": [10, 28], "uv_size": [-4, 3]},
								"south": {"uv": [7, 36], "uv_size": [-1, 3]},
								"west": {"uv": [6, 28], "uv_size": [-4, 3]},
								"up": {"uv": [11, 33], "uv_size": [-1, 4]},
								"down": {"uv": [30, 37], "uv_size": [-1, -4]}
							}
						},
						{
							"origin": [7.73267, 18.03587, -1.88496],
							"size": [1.02816, 2.74176, 3.76992],
							"pivot": [8.36099, 19.40675, 0],
							"rotation": [0, 0, 5],
							"uv": {
								"north": {"uv": [15, 36], "uv_size": [-1, 2]},
								"east": {"uv": [36, 1], "uv_size": [-3, 2]},
								"south": {"uv": [16, 36], "uv_size": [-1, 2]},
								"west": {"uv": [30, 31], "uv_size": [-3, 2]},
								"up": {"uv": [14, 36], "uv_size": [-1, 3]},
								"down": {"uv": [37, 16], "uv_size": [-1, -3]}
							}
						},
						{
							"origin": [3.62003, 18.49283, -2.34192],
							"size": [4.79808, 1.82784, 4.68384],
							"pivot": [6.01907, 19.40675, 0],
							"rotation": [0, 0, -5],
							"uv": {
								"north": {"uv": [23, 31], "uv_size": [-4, 2]},
								"east": {"uv": [36, 15], "uv_size": [-4, 2]},
								"south": {"uv": [36, 13], "uv_size": [-4, 2]},
								"west": {"uv": [27, 31], "uv_size": [-4, 2]},
								"up": {"uv": [6, 24], "uv_size": [-4, 4]},
								"down": {"uv": [10, 28], "uv_size": [-4, -4]}
							}
						},
						{
							"origin": [4.30547, 23.86211, -2.45616],
							"size": [2.51328, 1.02816, 4.79808],
							"uv": {
								"north": {"uv": [30, 22], "uv_size": [-2, 1]},
								"east": {"uv": [26, 34], "uv_size": [-4, 1]},
								"south": {"uv": [38, 1], "uv_size": [-2, 1]},
								"west": {"uv": [38, 11], "uv_size": [-4, 1]},
								"up": {"uv": [17, 31], "uv_size": [-2, 4]},
								"down": {"uv": [19, 35], "uv_size": [-2, -4]}
							}
						},
						{
							"origin": [4.2712, 24.39904, -1.25664],
							"size": [1.25664, 2.2848, 2.39904],
							"uv": {
								"north": {"uv": [12, 47], "uv_size": [1, 2]},
								"east": {"uv": [17, 44], "uv_size": [2, 2]},
								"south": {"uv": [12, 47], "uv_size": [1, 2]},
								"west": {"uv": [12, 44], "uv_size": [2, 2]},
								"up": {"uv": [18, 40], "uv_size": [-1, -2]},
								"down": {"uv": [13.1, 40], "uv_size": [-1.1, -2]}
							}
						},
						{
							"origin": [4.38544, 24.92454, -1.94208],
							"size": [1.02816, 2.17056, 2.17056],
							"pivot": [4.89952, 25.54144, -0.11424],
							"rotation": [57.5, 0, 0],
							"uv": {
								"north": {"uv": [0, 38], "uv_size": [0.9, 1.9]},
								"east": {"uv": [7, 48], "uv_size": [-2, 1]},
								"south": {"uv": [0, 38], "uv_size": [0.9, 1.9]},
								"west": {"uv": [5, 48], "uv_size": [2, 1]},
								"up": {"uv": [8.9, 40.9], "uv_size": [-0.9, -1.9]},
								"down": {"uv": [0.9, 39.9], "uv_size": [-0.9, -1.9]}
							}
						},
						{
							"origin": [4.38544, 24.8103, -0.22848],
							"size": [1.02816, 2.17056, 2.17056],
							"pivot": [4.89952, 25.54144, 0.11424],
							"rotation": [-57.5, 0, 0],
							"uv": {
								"north": {"uv": [0.9, 0], "uv_size": [-0.9, 1.9]},
								"east": {"uv": [5, 48], "uv_size": [2, 1]},
								"south": {"uv": [0.9, 0], "uv_size": [-0.9, 1.9]},
								"west": {"uv": [7, 48], "uv_size": [-2, 1]},
								"up": {"uv": [8.9, 39], "uv_size": [-0.9, 1.9]},
								"down": {"uv": [0.9, 0], "uv_size": [-0.9, 1.9]}
							}
						}
					]
				},
				{
					"name": "bipedRightLeg",
					"pivot": [-2, 12, 0]
				},
				{
					"name": "armorRightLeg",
					"parent": "bipedRightLeg",
					"pivot": [-1.9, 12, 0],
					"cubes": [
						{
							"origin": [-3.03, 5.19, -2.599],
							"size": [2.26, 2.26, 2.26],
							"uv": {
								"north": {"uv": [5, 34], "uv_size": [2, 2]},
								"east": {"uv": [0, 35], "uv_size": [2, 2]},
								"south": {"uv": [2, 35], "uv_size": [2, 2]},
								"west": {"uv": [35, 6], "uv_size": [2, 2]},
								"up": {"uv": [7, 35], "uv_size": [2, 2]},
								"down": {"uv": [11, 37], "uv_size": [2, -2]}
							}
						},
						{
							"origin": [-4.386, 6.772, -2.486],
							"size": [4.859, 3.955, 4.859],
							"uv": {
								"north": {"uv": [18, 28], "uv_size": [4, 3]},
								"east": {"uv": [28, 19], "uv_size": [4, 3]},
								"south": {"uv": [22, 28], "uv_size": [4, 3]},
								"west": {"uv": [29, 0], "uv_size": [4, 3]},
								"up": {"uv": [24, 15], "uv_size": [4, 4]},
								"down": {"uv": [18, 28], "uv_size": [4, -4]}
							}
						},
						{
							"origin": [-4.386, 1.913, -2.486],
							"size": [4.859, 3.955, 1.017],
							"uv": {
								"north": {"uv": [25, 0], "uv_size": [4, 4]},
								"east": {"uv": [4, 35], "uv_size": [1, 4]},
								"south": {"uv": [26, 9], "uv_size": [4, 4]},
								"west": {"uv": [9, 35], "uv_size": [1, 4]},
								"up": {"uv": [30, 35], "uv_size": [4, 1]},
								"down": {"uv": [34, 36], "uv_size": [4, -1]}
							}
						},
						{
							"origin": [-4.386, 2.478, -1.469],
							"size": [4.859, 2.825, 3.842],
							"uv": {
								"north": {"uv": [32, 17], "uv_size": [4, 2]},
								"east": {"uv": [7, 33], "uv_size": [3, 2]},
								"south": {"uv": [32, 19], "uv_size": [4, 2]},
								"west": {"uv": [19, 33], "uv_size": [3, 2]},
								"up": {"uv": [30, 9], "uv_size": [4, 3]},
								"down": {"uv": [30, 25], "uv_size": [4, -3]}
							}
						},
						{
							"origin": [-4.273, 10.162, -2.4295],
							"size": [4.746, 1.356, 4.746],
							"pivot": [-1.9565, 11.0095, -0.0565],
							"rotation": [0, 0, 10],
							"uv": {
								"north": {"uv": [13, 35], "uv_size": [4, 1]},
								"east": {"uv": [17, 35], "uv_size": [4, 1]},
								"south": {"uv": [21, 35], "uv_size": [4, 1]},
								"west": {"uv": [25, 35], "uv_size": [4, 1]},
								"up": {"uv": [24, 19], "uv_size": [4, 4]},
								"down": {"uv": [22, 28], "uv_size": [4, -4]}
							}
						}
					]
				},
				{
					"name": "armorRightBoot",
					"parent": "bipedRightLeg",
					"pivot": [-2, 13.3, -0.1],
					"cubes": [
						{
							"origin": [-4.373, -0.373, -2.586],
							"size": [4.746, 2.26, 4.859],
							"uv": {
								"north": {"uv": [32, 25], "uv_size": [4, 2]},
								"east": {"uv": [32, 27], "uv_size": [4, 2]},
								"south": {"uv": [32, 29], "uv_size": [4, 2]},
								"west": {"uv": [32, 31], "uv_size": [4, 2]},
								"up": {"uv": [26, 23], "uv_size": [4, 4]},
								"down": {"uv": [26, 31], "uv_size": [4, -4]}
							}
						}
					]
				},
				{
					"name": "bipedLeftLeg",
					"pivot": [2, 12, 0]
				},
				{
					"name": "armorLeftLeg",
					"parent": "bipedLeftLeg",
					"pivot": [2, 12, 0],
					"cubes": [
						{
							"origin": [-0.373, 10.162, -2.4295],
							"size": [4.746, 1.356, 4.746],
							"pivot": [2.0565, 11.0095, -0.0565],
							"rotation": [0, 0, -10],
							"uv": {
								"north": {"uv": [17, 35], "uv_size": [-4, 1]},
								"east": {"uv": [29, 35], "uv_size": [-4, 1]},
								"south": {"uv": [25, 35], "uv_size": [-4, 1]},
								"west": {"uv": [21, 35], "uv_size": [-4, 1]},
								"up": {"uv": [28, 19], "uv_size": [-4, 4]},
								"down": {"uv": [26, 28], "uv_size": [-4, -4]}
							}
						},
						{
							"origin": [0.87, 5.19, -2.599],
							"size": [2.26, 2.26, 2.26],
							"uv": {
								"north": {"uv": [7, 34], "uv_size": [-2, 2]},
								"east": {"uv": [37, 6], "uv_size": [-2, 2]},
								"south": {"uv": [4, 35], "uv_size": [-2, 2]},
								"west": {"uv": [2, 35], "uv_size": [-2, 2]},
								"up": {"uv": [9, 35], "uv_size": [-2, 2]},
								"down": {"uv": [13, 37], "uv_size": [-2, -2]}
							}
						},
						{
							"origin": [-0.373, 6.772, -2.486],
							"size": [4.859, 3.955, 4.859],
							"uv": {
								"north": {"uv": [22, 28], "uv_size": [-4, 3]},
								"east": {"uv": [33, 0], "uv_size": [-4, 3]},
								"south": {"uv": [26, 28], "uv_size": [-4, 3]},
								"west": {"uv": [32, 19], "uv_size": [-4, 3]},
								"up": {"uv": [28, 15], "uv_size": [-4, 4]},
								"down": {"uv": [22, 28], "uv_size": [-4, -4]}
							}
						},
						{
							"origin": [-0.373, 1.913, -2.486],
							"size": [4.859, 3.955, 1.017],
							"uv": {
								"north": {"uv": [29, 0], "uv_size": [-4, 4]},
								"east": {"uv": [10, 35], "uv_size": [-1, 4]},
								"south": {"uv": [30, 9], "uv_size": [-4, 4]},
								"west": {"uv": [5, 35], "uv_size": [-1, 4]},
								"up": {"uv": [34, 35], "uv_size": [-4, 1]},
								"down": {"uv": [38, 36], "uv_size": [-4, -1]}
							}
						},
						{
							"origin": [-0.373, 2.478, -1.469],
							"size": [4.859, 2.825, 3.842],
							"uv": {
								"north": {"uv": [36, 17], "uv_size": [-4, 2]},
								"east": {"uv": [22, 33], "uv_size": [-3, 2]},
								"south": {"uv": [36, 19], "uv_size": [-4, 2]},
								"west": {"uv": [10, 33], "uv_size": [-3, 2]},
								"up": {"uv": [34, 9], "uv_size": [-4, 3]},
								"down": {"uv": [34, 25], "uv_size": [-4, -3]}
							}
						}
					]
				},
				{
					"name": "armorLeftBoot",
					"parent": "bipedLeftLeg",
					"pivot": [2, 13.3, 0],
					"cubes": [
						{
							"origin": [-0.373, -0.373, -2.486],
							"size": [4.746, 2.26, 4.859],
							"uv": {
								"north": {"uv": [36, 25], "uv_size": [-4, 2]},
								"east": {"uv": [36, 31], "uv_size": [-4, 2]},
								"south": {"uv": [36, 29], "uv_size": [-4, 2]},
								"west": {"uv": [36, 27], "uv_size": [-4, 2]},
								"up": {"uv": [30, 23], "uv_size": [-4, 4]},
								"down": {"uv": [30, 31], "uv_size": [-4, -4]}
							}
						}
					]
				}
			]
		}
	]
}